[{"company":"Yuma Energy, Inc. 9.25% Series ","symbol":"YUMA-PA","price":"1.15","change":"-1.95","percentage":"-62.93%","lastTrade":"Jan 20 4:00 PM EST","volume":"46,519"},{"company":"Texas Capital Bancshares, Inc.","symbol":"TCBIW","price":"24.55","change":"-14.06","percentage":"-36.42%","lastTrade":"Jan 20 3:59 PM EST","volume":"1,682"},{"company":"Nxt-ID, Inc.","symbol":"NXTD","price":"0.8101","change":"-0.4299","percentage":"-34.67%","lastTrade":"Jan 20 4:00 PM EST","volume":"7,631,630"},{"company":"UBS ETRACS 2xMonthly Lvg S&P MLP ETN","symbol":"MLPV","price":"4.63","change":"-2.02","percentage":"-30.43%","lastTrade":"Jan 20 4:00 PM EST","volume":"26,561"},{"company":"Emerge Energy Services LP","symbol":"EMES","price":"2.25","change":"-0.78","percentage":"-25.74%","lastTrade":"Jan 20 4:01 PM EST","volume":"1,756,958"},{"company":"Erin Energy Corporation","symbol":"ERN","price":"1.62","change":"-0.51","percentage":"-23.94%","lastTrade":"Jan 20 4:02 PM EST","volume":"1,028,113"},{"company":"China Yida Holding, Co.","symbol":"CNYD","price":"1.71","change":"-0.52","percentage":"-23.45%","lastTrade":"Jan 20 3:59 PM EST","volume":"44,669"},{"company":"UBS ETRACS 2xM Lvg Lng Alrn MLP Infr ETN","symbol":"MLPL","price":"8.74","change":"-2.67","percentage":"-23.40%","lastTrade":"Jan 20 4:00 PM EST","volume":"1,766,085"},{"company":"Washington Federal, Inc.","symbol":"WAFDW","price":"4.34","change":"-1.29","percentage":"-22.91%","lastTrade":"Jan 20 3:59 PM EST","volume":"2,306"},{"company":"C&J Energy Services, Ltd.","symbol":"CJES","price":"1.58","change":"-0.43","percentage":"-21.39%","lastTrade":"Jan 20 4:00 PM EST","volume":"5,250,439"},{"company":"Carver Bancorp, Inc.","symbol":"CARV","price":"2.33","change":"-0.62","percentage":"-21.02%","lastTrade":"Jan 20 3:59 PM EST","volume":"31,831"},{"company":"Gastar Exploration Inc. Pfd Ser","symbol":"GST-PB","price":"7.00","change":"-1.83","percentage":"-20.72%","lastTrade":"Jan 20 4:00 PM EST","volume":"53,461"},{"company":"DB Commodity Double Long ETN","symbol":"DYY","price":"2.40","change":"-0.60","percentage":"-20.00%","lastTrade":"Jan 20 4:00 PM EST","volume":"3,332"},{"company":"Stone Energy Corp.","symbol":"SGY","price":"1.93","change":"-0.48","percentage":"-19.92%","lastTrade":"Jan 20 4:01 PM EST","volume":"7,888,750"},{"company":"Barnwell Industries, Inc.","symbol":"BRN","price":"1.45","change":"-0.35","percentage":"-19.44%","lastTrade":"Jan 20 4:00 PM EST","volume":"7,635"},{"company":"Credit Suisse X-Links Cmdty Benchmk ETN","symbol":"CSCB","price":"8.9501","change":"-2.1499","percentage":"-19.37%","lastTrade":"Jan 20 2:18 PM EST","volume":"200"},{"company":"Western Gas Equity Partners, LP","symbol":"WGP","price":"21.25","change":"-5.00","percentage":"-19.05%","lastTrade":"Jan 20 4:02 PM EST","volume":"1,230,785"},{"company":"Golar LNG Ltd.","symbol":"GLNG","price":"10.04","change":"-2.35","percentage":"-18.97%","lastTrade":"Jan 20 3:59 PM EST","volume":"4,512,468"},{"company":"EnerJex Resources, Inc. 10% Ser","symbol":"ENRJ-P","price":"0.92","change":"-0.21","percentage":"-18.70%","lastTrade":"Jan 20 4:00 PM EST","volume":"10,645"},{"company":"Hugoton Royalty Trust","symbol":"HGT","price":"0.98","change":"-0.22","percentage":"-18.33%","lastTrade":"Jan 20 4:00 PM EST","volume":"635,535"},{"company":"Code Rebel Corp","symbol":"CDRB","price":"2.51","change":"-0.53","percentage":"-17.43%","lastTrade":"Jan 20 4:00 PM EST","volume":"163,603"},{"company":"Ryerson Holding Corporation","symbol":"RYI","price":"2.77","change":"-0.57","percentage":"-17.07%","lastTrade":"Jan 20 4:00 PM EST","volume":"256,477"},{"company":"Viking Therapeutics, Inc.","symbol":"VKTX","price":"2.11","change":"-0.43","percentage":"-16.93%","lastTrade":"Jan 20 3:59 PM EST","volume":"123,432"},{"company":"NovoCure Limited","symbol":"NVCR","price":"14.23","change":"-2.83","percentage":"-16.59%","lastTrade":"Jan 20 4:00 PM EST","volume":"1,117,502"},{"company":"Fluidigm Corporation","symbol":"FLDM","price":"6.22","change":"-1.22","percentage":"-16.40%","lastTrade":"Jan 20 4:00 PM EST","volume":"2,237,147"},{"company":"Leading Brands Inc.","symbol":"LBIX","price":"1.80","change":"-0.35","percentage":"-16.28%","lastTrade":"Jan 20 3:59 PM EST","volume":"500"},{"company":"TCB-WT","symbol":"TCB-WT","price":"1.50","change":"-0.29","percentage":"-16.20%","lastTrade":"Jan 20 1:56 PM EST","volume":"101"},{"company":"PrimeEnergy Corp.","symbol":"PNRG","price":"42.00","change":"-8.00","percentage":"-16.00%","lastTrade":"Jan 20 12:31 PM EST","volume":"1,562"},{"company":"UBIC, Inc.","symbol":"UBIC","price":"13.27","change":"-2.32","percentage":"-14.88%","lastTrade":"Jan 20 1:45 PM EST","volume":"374"},{"company":"Atlantic American Corp.","symbol":"AAME","price":"3.93","change":"-0.68","percentage":"-14.69%","lastTrade":"Jan 20 4:00 PM EST","volume":"18,561"},{"company":"Direxion Daily Nat Gas Rltd Bear 3X ETF","symbol":"GASX","price":"108.74","change":"-18.16","percentage":"-14.31%","lastTrade":"Jan 20 4:00 PM EST","volume":"30,075"},{"company":"Connecture, Inc.","symbol":"CNXR","price":"1.80","change":"-0.30","percentage":"-14.29%","lastTrade":"Jan 20 4:00 PM EST","volume":"164,539"},{"company":"Lehman ABS Corporation Corporat","symbol":"XKE","price":"4.35","change":"-0.71","percentage":"-14.03%","lastTrade":"Jan 20 4:00 PM EST","volume":"8,545"},{"company":"NuStar GP Holdings, LLC","symbol":"NSH","price":"13.17","change":"-2.13","percentage":"-13.92%","lastTrade":"Jan 20 4:02 PM EST","volume":"333,195"},{"company":"Novatel Wireless Inc.","symbol":"MIFI","price":"1.00","change":"-0.16","percentage":"-13.79%","lastTrade":"Jan 20 3:59 PM EST","volume":"1,821,422"},{"company":"Anadarko Petroleum Corporation","symbol":"AEUA","price":"23.25","change":"-3.66","percentage":"-13.60%","lastTrade":"Jan 20 4:00 PM EST","volume":"34,139"},{"company":"RiT Technologies Ltd.","symbol":"RITT","price":"1.03","change":"-0.16","percentage":"-13.45%","lastTrade":"Jan 20 4:00 PM EST","volume":"216,830"},{"company":"Direxion Daily S&P Biotech Bear 3X ETF","symbol":"LABD","price":"56.74","change":"-8.65","percentage":"-13.23%","lastTrade":"Jan 20 4:00 PM EST","volume":"1,122,553"},{"company":"Gastar Exploration 8.625% Serie","symbol":"GST-PA","price":"6.47","change":"-0.98","percentage":"-13.15%","lastTrade":"Jan 20 4:00 PM EST","volume":"33,605"},{"company":"ASB-WT","symbol":"ASB-WT","price":"1.87","change":"-0.28","percentage":"-13.13%","lastTrade":"Jan 20 4:00 PM EST","volume":"50,700"},{"company":"Pioneer Energy Services Corp.","symbol":"PES","price":"1.06","change":"-0.16","percentage":"-13.11%","lastTrade":"Jan 20 4:00 PM EST","volume":"2,066,729"},{"company":"Parker Drilling Co.","symbol":"PKD","price":"1.07","change":"-0.16","percentage":"-13.01%","lastTrade":"Jan 20 4:01 PM EST","volume":"2,071,357"},{"company":"EnLink Midstream, LLC","symbol":"ENLC","price":"9.95","change":"-1.48","percentage":"-12.95%","lastTrade":"Jan 20 4:01 PM EST","volume":"1,085,486"},{"company":"SUNTRUST BANKS, INC. WARRANTS ","symbol":"STI-WTA","price":"6.8775","change":"-1.0225","percentage":"-12.94%","lastTrade":"Jan 20 4:00 PM EST","volume":"7,525"},{"company":"Teekay Corporation","symbol":"TK","price":"4.92","change":"-0.72","percentage":"-12.77%","lastTrade":"Jan 20 4:05 PM EST","volume":"5,494,104"},{"company":"Jaguar Animal Health, Inc.","symbol":"JAGX","price":"2.67","change":"-0.39","percentage":"-12.75%","lastTrade":"Jan 20 3:53 PM EST","volume":"34,036"},{"company":"BioAmber Inc.","symbol":"BIOA","price":"3.70","change":"-0.54","percentage":"-12.74%","lastTrade":"Jan 20 4:02 PM EST","volume":"164,715"},{"company":"Benitec Biopharma Limited","symbol":"BNTCW","price":"1.66","change":"-0.24","percentage":"-12.63%","lastTrade":"Jan 20 1:17 PM EST","volume":"15,901"},{"company":"Alon Blue Square Israel Ltd","symbol":"BSI","price":"5.08","change":"-0.73","percentage":"-12.56%","lastTrade":"Jan 20 4:05 PM EST","volume":"289,227"},{"company":"ClearBridge Energy MLP Total Return Fund Inc.","symbol":"CTR","price":"7.06","change":"-1.01","percentage":"-12.52%","lastTrade":"Jan 20 4:02 PM EST","volume":"812,900"}]