[{"company":"Alimera Sciences, Inc.","symbol":"ALIM","price":"2.56","change":"+0.54","percentage":"+26.73%","lastTrade":"Oct 7 4:00 PM EDT","volume":"694,686"},{"company":"Marrone Bio Innovations, Inc.","symbol":"MBII","price":"2.77","change":"+0.51","percentage":"+22.57%","lastTrade":"Oct 7 4:00 PM EDT","volume":"122,205"},{"company":"Pacific Biosciences of California, Inc.","symbol":"PACB","price":"7.80","change":"+1.43","percentage":"+22.45%","lastTrade":"Oct 7 4:00 PM EDT","volume":"11,112,226"},{"company":"Evoke Pharma, Inc.","symbol":"EVOK","price":"3.95","change":"+0.65","percentage":"+19.70%","lastTrade":"Oct 7 4:00 PM EDT","volume":"1,452,584"},{"company":"Nuverra Environmental Solutions, Inc.","symbol":"NES","price":"2.00","change":"+0.31","percentage":"+18.34%","lastTrade":"Oct 7 4:02 PM EDT","volume":"615,859"},{"company":"Copa Holdings SA","symbol":"CPA","price":"54.11","change":"+8.12","percentage":"+17.66%","lastTrade":"Oct 7 4:00 PM EDT","volume":"2,224,069"},{"company":"WPCS International Incorporated","symbol":"WPCS","price":"1.6199","change":"+0.2399","percentage":"+17.38%","lastTrade":"Oct 7 3:59 PM EDT","volume":"796,999"},{"company":"Goodrich Petroleum Corporation ","symbol":"GDP-PC","price":"2.32","change":"+0.34","percentage":"+17.36%","lastTrade":"Oct 7 4:00 PM EDT","volume":"98,703"},{"company":"Goodrich Petroleum Corporation ","symbol":"GDP-PD","price":"2.23","change":"+0.32","percentage":"+17.05%","lastTrade":"Oct 7 4:02 PM EDT","volume":"91,768"},{"company":"NantKwest, Inc.","symbol":"NK","price":"13.45","change":"+1.90","percentage":"+16.45%","lastTrade":"Oct 7 4:00 PM EDT","volume":"596,818"},{"company":"China Digital TV Holding Co., Ltd.","symbol":"STV","price":"2.22","change":"+0.31","percentage":"+16.23%","lastTrade":"Oct 7 4:01 PM EDT","volume":"318,864"},{"company":"PharmAthene, Inc.","symbol":"PIP","price":"1.61","change":"+0.22","percentage":"+15.83%","lastTrade":"Oct 7 4:03 PM EDT","volume":"596,822"},{"company":"Verastem, Inc.","symbol":"VSTM","price":"2.12","change":"+0.28","percentage":"+15.22%","lastTrade":"Oct 7 3:59 PM EDT","volume":"2,300,037"},{"company":"Vestin Realty Mortgage I, Inc","symbol":"VRTA","price":"4.65","change":"+0.61","percentage":"+15.10%","lastTrade":"Oct 7 2:55 PM EDT","volume":"3,046"},{"company":"ContraFect Corporation","symbol":"CFRXW","price":"1.45","change":"+0.19","percentage":"+15.08%","lastTrade":"Oct 7 3:10 PM EDT","volume":"100"},{"company":"MeetMe, Inc.","symbol":"MEET","price":"1.91","change":"+0.25","percentage":"+15.06%","lastTrade":"Oct 7 4:00 PM EDT","volume":"3,175,924"},{"company":"MDGN-WT","symbol":"MDGN-WT","price":"2.24","change":"+0.29","percentage":"+14.87%","lastTrade":"Oct 7 4:00 PM EDT","volume":"650"},{"company":"UBS ETRACS 2xMonthly Lvg S&P MLP Idx ETN","symbol":"MLPV","price":"16.60","change":"+2.10","percentage":"+14.48%","lastTrade":"Oct 7 4:00 PM EDT","volume":"1,460"},{"company":"Cross Country Healthcare, Inc.","symbol":"CCRN","price":"14.62","change":"+1.84","percentage":"+14.40%","lastTrade":"Oct 7 4:00 PM EDT","volume":"991,210"},{"company":"Westport Innovations Inc.","symbol":"WPRT","price":"3.44","change":"+0.43","percentage":"+14.29%","lastTrade":"Oct 7 4:00 PM EDT","volume":"935,011"},{"company":"Lion Biotechnologies, Inc.","symbol":"LBIO","price":"6.43","change":"+0.80","percentage":"+14.21%","lastTrade":"Oct 7 4:00 PM EDT","volume":"832,763"},{"company":"Teck Resources Limited","symbol":"TCK","price":"6.79","change":"+0.84","percentage":"+14.12%","lastTrade":"Oct 7 4:06 PM EDT","volume":"23,324,735"},{"company":"UBIC, Inc.","symbol":"UBIC","price":"13.59","change":"+1.68","percentage":"+14.11%","lastTrade":"Oct 7 10:46 AM EDT","volume":"864"},{"company":"Voxeljet AG","symbol":"VJET","price":"6.73","change":"+0.82","percentage":"+13.87%","lastTrade":"Oct 7 4:00 PM EDT","volume":"309,841"},{"company":"Dynamic Materials Corp.","symbol":"BOOM","price":"10.46","change":"+1.27","percentage":"+13.82%","lastTrade":"Oct 7 4:00 PM EDT","volume":"178,187"},{"company":"Sphere 3D Corp.","symbol":"ANY","price":"3.12","change":"+0.37","percentage":"+13.45%","lastTrade":"Oct 7 4:00 PM EDT","volume":"230,938"},{"company":"Global X China Energy ETF","symbol":"CHIE","price":"12.08","change":"+1.43","percentage":"+13.43%","lastTrade":"Oct 7 4:00 PM EDT","volume":"2,839"},{"company":"Core-Mark Holding Company, Inc.","symbol":"CORE","price":"73.30","change":"+8.53","percentage":"+13.17%","lastTrade":"Oct 7 4:00 PM EDT","volume":"1,419,923"},{"company":"Systemax Inc.","symbol":"SYX","price":"8.80","change":"+1.02","percentage":"+13.11%","lastTrade":"Oct 7 4:02 PM EDT","volume":"24,847"},{"company":"Mexco Energy Corporation","symbol":"MXC","price":"3.05","change":"+0.35","percentage":"+12.96%","lastTrade":"Oct 7 4:00 PM EDT","volume":"13,700"},{"company":"Fuel Systems Solutions, Inc.","symbol":"FSYS","price":"6.60","change":"+0.74","percentage":"+12.63%","lastTrade":"Oct 7 3:59 PM EDT","volume":"132,832"},{"company":"Dicerna Pharmaceuticals, Inc.","symbol":"DRNA","price":"9.27","change":"+1.03","percentage":"+12.50%","lastTrade":"Oct 7 4:00 PM EDT","volume":"146,491"},{"company":"Qumu Corporation","symbol":"QUMU","price":"4.50","change":"+0.50","percentage":"+12.50%","lastTrade":"Oct 7 3:59 PM EDT","volume":"16,893"},{"company":"Aerie Pharmaceuticals, Inc.","symbol":"AERI","price":"21.25","change":"+2.35","percentage":"+12.43%","lastTrade":"Oct 7 4:00 PM EDT","volume":"1,099,868"},{"company":"Direxion Daily FTSE China Bull 3X ETF","symbol":"YINN","price":"22.61","change":"+2.46","percentage":"+12.21%","lastTrade":"Oct 7 4:00 PM EDT","volume":"1,538,136"},{"company":"Entellus Medical, Inc.","symbol":"ENTL","price":"20.18","change":"+2.18","percentage":"+12.11%","lastTrade":"Oct 7 4:00 PM EDT","volume":"168,422"},{"company":"AmpliPhi Biosciences Corporation","symbol":"APHB","price":"5.15","change":"+0.55","percentage":"+11.96%","lastTrade":"Oct 7 4:00 PM EDT","volume":"43,400"},{"company":"EASTMAN KODAK CO. WARRANTS EXP","symbol":"KODK-WT","price":"3.75","change":"+0.40","percentage":"+11.94%","lastTrade":"Oct 7 3:15 PM EDT","volume":"630"},{"company":"ProShares Ultra MSCI Mexico Capped IMI","symbol":"UMX","price":"27.80","change":"+2.95","percentage":"+11.89%","lastTrade":"Oct 7 11:01 AM EDT","volume":"312"},{"company":"SunEdison, Inc.","symbol":"SUNE","price":"9.72","change":"+1.03","percentage":"+11.85%","lastTrade":"Oct 7 4:05 PM EDT","volume":"55,089,896"},{"company":"Quantum Fuel Systems Technologies Worldwide Inc.","symbol":"QTWW","price":"1.42","change":"+0.15","percentage":"+11.81%","lastTrade":"Oct 7 4:00 PM EDT","volume":"197,214"},{"company":"Galectin Therapeutics, Inc.","symbol":"GALT","price":"2.67","change":"+0.28","percentage":"+11.72%","lastTrade":"Oct 7 4:00 PM EDT","volume":"260,829"},{"company":"Vital Therapies, Inc.","symbol":"VTL","price":"4.51","change":"+0.47","percentage":"+11.63%","lastTrade":"Oct 7 4:00 PM EDT","volume":"353,544"},{"company":"Tetraphase Pharmaceuticals, Inc.","symbol":"TTPH","price":"9.29","change":"+0.96","percentage":"+11.52%","lastTrade":"Oct 7 4:00 PM EDT","volume":"1,982,530"},{"company":"China Distance Education Holdings Limited","symbol":"DL","price":"14.04","change":"+1.44","percentage":"+11.43%","lastTrade":"Oct 7 4:02 PM EDT","volume":"158,467"},{"company":"BioAmber Inc.","symbol":"BIOA","price":"8.12","change":"+0.83","percentage":"+11.39%","lastTrade":"Oct 7 4:06 PM EDT","volume":"200,499"},{"company":"Amicus Therapeutics, Inc.","symbol":"FOLD","price":"7.01","change":"+0.71","percentage":"+11.27%","lastTrade":"Oct 7 4:00 PM EDT","volume":"8,669,279"},{"company":"CytRx Corporation","symbol":"CYTR","price":"2.88","change":"+0.29","percentage":"+11.20%","lastTrade":"Oct 7 4:00 PM EDT","volume":"677,889"},{"company":"Global Payments Inc.","symbol":"GPN","price":"128.20","change":"+12.83","percentage":"+11.12%","lastTrade":"Oct 7 4:03 PM EDT","volume":"2,275,740"},{"company":"Bovie Medical Corporation","symbol":"BVX","price":"2.10","change":"+0.21","percentage":"+11.11%","lastTrade":"Oct 7 4:00 PM EDT","volume":"84,834"}]